sobolsampling/__init__.py
sobolsampling/sobol_new.py
sobolsampling/sobolcoeff.csv
sobolsampling-0.1.2.dist-info/DESCRIPTION.rst
sobolsampling-0.1.2.dist-info/METADATA
sobolsampling-0.1.2.dist-info/RECORD
sobolsampling-0.1.2.dist-info/WHEEL
sobolsampling-0.1.2.dist-info/metadata.json
sobolsampling-0.1.2.dist-info/top_level.txt
