Metadata-Version: 2.0
Name: sobolsampling
Version: 0.1.2
Summary: Sobol Sampling Package
Home-page: https://github.com/fazaghifari/SobolSampling
Author: Ghifari Adam F
Author-email: ghifariadamf@gmail.com
License: BSD-3
Download-URL: https://github.com/fazaghifari/SobolSampling/releases
Platform: UNKNOWN
Requires-Python: >=3.6.*
Requires-Dist: numpy
